mukairnlpv1/__init__.py
mukairnlpv1/lex_attrs.py
mukairnlpv1/stop_words.py
mukairnlpv1-1.0.0.dist-info/LICENSE
mukairnlpv1-1.0.0.dist-info/METADATA
mukairnlpv1-1.0.0.dist-info/WHEEL
mukairnlpv1-1.0.0.dist-info/top_level.txt
mukairnlpv1-1.0.0.dist-info/RECORD
