Metadata-Version: 2.1
Name: mukairnlpv1
Version: 1.0.0
Summary: For natural language processing
Home-page: https://github.com/pypa/sampleproject
Author: Bateesa
Author-email: tobiusaolo21@gmail.com
Classifier: Programming Language :: Python :: 3
Classifier: License :: OSI Approved :: MIT License
Classifier: Operating System :: OS Independent
Requires-Python: >=3.6
License-File: LICENSE
